{"client":"Thunder Client","collectionName":"PreNotebook","dateExported":"2021-09-23T13:33:06.043Z","version":"1.1","folders":[{"containerId":"","sortNum":10000,"name":"Authentication","_id":"77d642f9-dbb3-4bc7-9353-cdc72d57c83a","created":"2021-09-23T12:36:25.166Z"}],"requests":[{"containerId":"77d642f9-dbb3-4bc7-9353-cdc72d57c83a","sortNum":10000,"headers":[{"name":"Accept","value":"*/*"},{"name":"User-Agent","value":"Thunder Client (https://www.thunderclient.io)"},{"name":"Content-Type","value":"application/json"}],"colId":"37e22387-b092-4845-a6d9-c224ccf346c8","name":"createUser","url":"https://3002-copper-weasel-d2fln7y9.ws-us17.gitpod.io/api/auth/createuser/","method":"POST","modified":"2021-09-23T12:50:23.087Z","created":"2021-09-23T12:36:25.168Z","_id":"db85984f-9f5a-4e2b-8e77-a686efdf50b3","params":[],"body":{"type":"json","raw":"{\n    \"name\" : \"Shyam Sundar\",\n    \"username\" : \"shyam3211\",\n    \"email\" : \"shyamsundar3211@gmail.com\",\n    \"password\" : \"@23aaDsy^!#\"\n}","form":[]},"tests":[]},{"containerId":"77d642f9-dbb3-4bc7-9353-cdc72d57c83a","sortNum":20000,"headers":[{"name":"Accept","value":"*/*"},{"name":"User-Agent","value":"Thunder Client (https://www.thunderclient.io)"},{"name":"Content-Type","value":"application/json"}],"colId":"37e22387-b092-4845-a6d9-c224ccf346c8","name":"user login using credentials","url":"https://3002-copper-weasel-d2fln7y9.ws-us17.gitpod.io/api/auth/login/","method":"POST","modified":"2021-09-23T13:29:50.646Z","created":"2021-09-23T13:18:36.584Z","_id":"1f81dc97-baa3-4001-9457-62b1b4a18cf9","params":[],"body":{"type":"json","raw":"{\n    \"email\" : \"shyamsundar3211@gmail.com\",\n    \"password\" : \"@23aaDsy^!#\"\n}","form":[]},"tests":[]}]}
